{"id":1,"nom":"Robe Noire","photo":null,"photo_url":null,"images":[],"vendeur":{"id":1,"nom":"Lova Mirahasina","contact":"","user":2,"facebook_page_id":"952578764609147","facebook_page_name":"Pétales et papilles","tiktok_username":null,"is_demo_mode":false,"pages_facebook":[{"id":3,"page_id":"952578764609147","nom":"Pétales et papilles","statut":"pret","webhook_subscribed":true},{"id":4,"page_id":"885475067983343","nom":"Champignon pleurote","statut":"pret","webhook_subscribed":true},{"id":5,"page_id":"123065280889757","nom":"AZExpress","statut":"pret","webhook_subscribed":true}]},"variantes":[{"id":1,"taille":"M","couleur":"Noir","prix_unitaire":"45000.00","stock":10,"code_jp":"ROBENOIR"}]}